{
	"partitions" : [
		{
			"name" : "Top",
			"pins" : [
				{
					"name" : "stall_out",
					"strict" : false
				},
				{
					"name" : "inst1_tag[0]",
					"strict" : false
				},
				{
					"name" : "inst1_tag[1]",
					"strict" : false
				},
				{
					"name" : "inst1_tag[2]",
					"strict" : false
				},
				{
					"name" : "inst1_tag[3]",
					"strict" : false
				},
				{
					"name" : "inst1_tag[4]",
					"strict" : false
				},
				{
					"name" : "inst2_tag[1]",
					"strict" : false
				},
				{
					"name" : "inst2_tag[2]",
					"strict" : false
				},
				{
					"name" : "inst2_tag[3]",
					"strict" : false
				},
				{
					"name" : "inst2_tag[4]",
					"strict" : false
				},
				{
					"name" : "instruction1[0]",
					"strict" : false
				},
				{
					"name" : "instruction2[0]",
					"strict" : false
				},
				{
					"name" : "clk",
					"strict" : false
				},
				{
					"name" : "reset",
					"strict" : false
				}
			]
		}
	]
}